rangeen/__init__.py
rangeen/_colors.py
rangeen/_emotes.py
rangeen/_utils.py
rangeen-0.0.2.dist-info/LICENSE
rangeen-0.0.2.dist-info/METADATA
rangeen-0.0.2.dist-info/WHEEL
rangeen-0.0.2.dist-info/top_level.txt
rangeen-0.0.2.dist-info/RECORD
